{
  "manifest_version": "1.0",
  "processing_mode": "modulus_mask_thr_500",
  "csv_mode": "default_scalar",
  "input_root": "C:\\Users\\Conor O'Brien\\Desktop\\TEST Folder",
  "pattern": "*.tif;*.tiff",
  "files": [
    "C:\\Users\\Conor O'Brien\\Desktop\\TEST Folder\\PEGDA01TPO000SiNP_Sam01_S1_P__GrID000_LOC_RC001001-5.00x5.00-Modulus_Backward-251021-CRO.tiff",
    "C:\\Users\\Conor O'Brien\\Desktop\\TEST Folder\\PEGDA01TPO000SiNP_Sam01_S1_P__GrID001_LOC_RC001002-5.00x5.00-Modulus_Backward-251021-CRO.tiff",
    "C:\\Users\\Conor O'Brien\\Desktop\\TEST Folder\\PEGDA01TPO000SiNP_Sam01_S1_P__GrID002_LOC_RC001001-5.00x5.00-Modulus_Backward-251020-CRO.tiff",
    "C:\\Users\\Conor O'Brien\\Desktop\\TEST Folder\\PEGDA01TPO000SiNP_Sam01_S1_P__GrID002_LOC_RC001005-5.00x5.00-Modulus_Backward-251022-CRO.tiff",
    "C:\\Users\\Conor O'Brien\\Desktop\\TEST Folder\\PEGDA01TPO000SiNP_Sam01_S1_P__GrID003_LOC_RC001006-5.00x5.00-Modulus_Backward-251022-CRO.tiff",
    "C:\\Users\\Conor O'Brien\\Desktop\\TEST Folder\\PEGDA01TPO000SiNP_Sam01_S1_P__GrID005_LOC_RC001010-5.00x5.00-Modulus_Backward-251027-CRO.tiff",
    "C:\\Users\\Conor O'Brien\\Desktop\\TEST Folder\\PEGDA01TPO000SiNP_Sam01_S1_P__GrID006_LOC_RC001011-5.00x5.00-Modulus_Backward-251027-CRO.tiff"
  ],
  "input_filters": {
    "filters_applied": false,
    "include_regex": [],
    "exclude_regex": []
  },
  "output_dir": "C:\\Users\\Conor O'Brien\\Documents\\GitHub\\AFM-Data-Management\\out\\verify_raw_trunc_nodebug\\modulus_mask_thr_500\\config.modulus_mask_sweep",
  "output_csv": "C:\\Users\\Conor O'Brien\\Documents\\GitHub\\AFM-Data-Management\\out\\verify_raw_trunc_nodebug\\modulus_mask_thr_500\\config.modulus_mask_sweep\\summary.csv",
  "grid": {
    "index_base": 1,
    "filename_regex": "LOC_RC(?P<row>\\d{3})(?P<col>\\d{3})"
  },
  "channel_defaults": {
    "modulus_family": "modulus"
  },
  "mode_definition": {
    "channel_family": "modulus",
    "gwyddion_ops": [],
    "stats_source": "gwyddion",
    "mask": {
      "method": "threshold",
      "threshold": 500.0,
      "direction": "above",
      "include_equal": true,
      "on_empty": "blank"
    },
    "metric_type": "modulus",
    "units": "kPa",
    "expected_units": "kPa",
    "on_unit_mismatch": "warn",
    "assume_units": "kPa",
    "on_missing_units": "warn"
  },
  "csv_mode_definition": {
    "columns": [
      {
        "name": "source_file",
        "from": "core.source_file"
      },
      {
        "name": "mode",
        "from": "core.mode"
      },
      {
        "name": "avg_value",
        "from": "core.avg_value"
      },
      {
        "name": "std_value",
        "from": "core.std_value"
      },
      {
        "name": "units",
        "from": "core.units"
      },
      {
        "name": "n_valid",
        "from": "core.n_valid",
        "default": ""
      },
      {
        "name": "row_idx",
        "from": "grid.row_idx",
        "default": -1
      },
      {
        "name": "col_idx",
        "from": "grid.col_idx",
        "default": -1
      }
    ],
    "on_missing_field": "warn_null"
  },
  "unit_conversions": {
    "modulus_mask_thr_0": {
      "kPa": {
        "target": "kPa",
        "factor": 1.0
      },
      "MPa": {
        "target": "kPa",
        "factor": 1000.0
      },
      "GPa": {
        "target": "kPa",
        "factor": "1e6"
      },
      "Pa": {
        "target": "kPa",
        "factor": 0.001
      }
    },
    "modulus_mask_thr_500": {
      "kPa": {
        "target": "kPa",
        "factor": 1.0
      },
      "MPa": {
        "target": "kPa",
        "factor": 1000.0
      },
      "GPa": {
        "target": "kPa",
        "factor": "1e6"
      },
      "Pa": {
        "target": "kPa",
        "factor": 0.001
      }
    },
    "modulus_mask_thr_5000": {
      "kPa": {
        "target": "kPa",
        "factor": 1.0
      },
      "MPa": {
        "target": "kPa",
        "factor": 1000.0
      },
      "GPa": {
        "target": "kPa",
        "factor": "1e6"
      },
      "Pa": {
        "target": "kPa",
        "factor": 0.001
      }
    },
    "modulus_mask_thr_mid_30000": {
      "kPa": {
        "target": "kPa",
        "factor": 1.0
      },
      "MPa": {
        "target": "kPa",
        "factor": 1000.0
      },
      "GPa": {
        "target": "kPa",
        "factor": "1e6"
      },
      "Pa": {
        "target": "kPa",
        "factor": 0.001
      }
    },
    "modulus_mask_thr_max_60000": {
      "kPa": {
        "target": "kPa",
        "factor": 1.0
      },
      "MPa": {
        "target": "kPa",
        "factor": 1000.0
      },
      "GPa": {
        "target": "kPa",
        "factor": "1e6"
      },
      "Pa": {
        "target": "kPa",
        "factor": 0.001
      }
    },
    "modulus_mask_thr_high_100000": {
      "kPa": {
        "target": "kPa",
        "factor": 1.0
      },
      "MPa": {
        "target": "kPa",
        "factor": 1000.0
      },
      "GPa": {
        "target": "kPa",
        "factor": "1e6"
      },
      "Pa": {
        "target": "kPa",
        "factor": 0.001
      }
    }
  },
  "filename_parsing": {},
  "debug": {
    "enable": false,
    "level": "info",
    "artifacts": [
      "mask"
    ],
    "sample_limit": 2,
    "log_fields": [
      "units",
      "stats_source",
      "mixed_processing",
      "mask_counts",
      "stats_counts",
      "grid",
      "raw_stats"
    ]
  }
}